tcflow/EMD_OPs.py
tcflow/EMD_run.py
tcflow/__init__.py
tcflow/input_gen.py
tcflow/run_emd.py
tcflow/run_nemd.py
dflow_thermal_conductivity-0.0.2.dist-info/LICENSE
dflow_thermal_conductivity-0.0.2.dist-info/METADATA
dflow_thermal_conductivity-0.0.2.dist-info/WHEEL
dflow_thermal_conductivity-0.0.2.dist-info/top_level.txt
dflow_thermal_conductivity-0.0.2.dist-info/RECORD
