Metadata-Version: 2.1
Name: dflow-thermal-conductivity
Version: 0.0.2
Summary: A framework for thermal conductivity calculation based on EMD&NEMD methods
Home-page: https://github.com/gdbhcxhmjk-z/ThermalConductivity-Workflow.git
Author: Wenjie Zhang
Author-email: gdbhcxhmjk@163.com
Classifier: Programming Language :: Python :: 3
Classifier: License :: OSI Approved :: Apache Software License
Classifier: Operating System :: OS Independent
Provides: dflowTC
Requires-Python: >=3.8
License-File: LICENSE
Requires-Dist: pydflow (>=1.6.27)
Requires-Dist: lbg (>=1.2.13)
Requires-Dist: dpdata (>=0.2.7)
Requires-Dist: matplotlib (>=3.6.3)
Requires-Dist: sportran
Requires-Dist: numpy
